dbcp/__init__.py
dbcp/atoms.py
dbcp/error.py
dbcp/fix.py
dbcp/problem.py
dbcp/transform.py
dbcp-0.2.0.dist-info/METADATA
dbcp-0.2.0.dist-info/WHEEL
dbcp-0.2.0.dist-info/licenses/LICENSE
dbcp-0.2.0.dist-info/RECORD
