Metadata-Version: 2.4
Name: dbcp
Version: 0.2.0
Summary: A CVXPY extension for disciplined biconvex programming.
Project-URL: repository, https://github.com/nrgrp/dbcp
Author: Joschka Boedecker
Author-email: Hao Zhu <zhuh@cs.uni-freiburg.de>
License-Expression: MIT
License-File: LICENSE
Keywords: biconvex optimization,convex optimization,disciplined biconvex programming,disciplined convex programming
Requires-Python: >=3.12
Requires-Dist: cvxpy>=1.7.3
Requires-Dist: numpy>=2.3.3
